[
  {
    "githubLogin": "baristabarita",
    "discordId": "353079332547330048",
    "channelId": "1429104737592021073",
    "active": true
  },
  {
    "githubLogin": "CaneteDominic",
    "discordId": "445577183562301440",
    "channelId": "1442479836529561691",
    "active": false
  },
  {
    "githubLogin": "chrstysrss",
    "discordId": "578929847087267842",
    "channelId": "1427382761693384764",
    "active": true
  },
  {
    "githubLogin": "coar14",
    "discordId": "775542965107556404",
    "channelId": "1438118754784514148",
    "active": true
  },
  {
    "githubLogin": "DanRed22",
    "discordId": "755454409978150982",
    "channelId": "1414727915655925870",
    "active": true
  },
  {
    "githubLogin": "hen-exe",
    "discordId": "222005303313432576",
    "channelId": "1427382883718266940",
    "active": false
  },
  {
    "githubLogin": "janggclyde",
    "discordId": "844357819943354378",
    "channelId": "1429104591458406491",
    "active": false
  },
  {
    "githubLogin": "JohnDegulacion",
    "discordId": "1151817856707731496",
    "channelId": "1430443998165602375",
    "active": true
  },
  {
    "githubLogin": "josephjamolod",
    "discordId": "826411357174759444",
    "channelId": "1432266833553002537",
    "active": false
  },
  {
    "githubLogin": "joshuacarl16",
    "discordId": "556353754568589312",
    "channelId": "1442794134246264922",
    "active": true
  },
  {
    "githubLogin": "PonPonc",
    "discordId": "439683020941819905",
    "channelId": "1429778488570675220",
    "active": true
  },
  {
    "githubLogin": "timmypintor",
    "discordId": "736460734694817885",
    "channelId": "1442794090784624721",
    "active": true
  },
  {
    "githubLogin": "xlaoll",
    "discordId": "319422373931778049",
    "channelId": "1442839861995503646",
    "active": true
  },
  {
    "githubLogin": "Katteu",
    "discordId": "601791377206018069",
    "channelId": "1414727915655925870",
    "active": true
  },
  {
    "githubLogin": "lancevincentsalera",
    "discordId": "749225007103606825",
    "channelId": "1512568385395888268",
    "active": true
  }
]
